ccbuild/__init__.py
ccbuild/_compile.py
ccbuild/_version.py
ccbuild/main.py
ccbuild/utils.py
ccbuild-1.1.0.dist-info/LICENSE
ccbuild-1.1.0.dist-info/METADATA
ccbuild-1.1.0.dist-info/WHEEL
ccbuild-1.1.0.dist-info/entry_points.txt
ccbuild-1.1.0.dist-info/top_level.txt
ccbuild-1.1.0.dist-info/RECORD
