Metadata-Version: 2.1
Name: ccbuild
Version: 1.1.0
Summary: UNKNOWN
Home-page: UNKNOWN
License: MIT
Platform: UNKNOWN
Requires-Python: >=2.7, <=3.10
Requires-Dist: setuptools
Requires-Dist: cython
